google_news_crawler/__init__.py
google_news_crawler/gnc.py
google_news_crawler/google_news_crawler.py
google_news_crawler/mine.feeds.py
google_news_crawler/util.py
google_news_crawler/datastore/__init__.py
google_news_crawler/datastore/base_datastore.py
google_news_crawler/datastore/es_datastore.py
google_news_crawler/datastore/fs_datastore.py
google_news_crawler/tests/__init__.py
google_news_crawler/tests/test_es.py
google_news_crawler/tests/test_gnc.py
google_news_crawler/tests/test_google_news_crawler.py
google_news_crawler-0.3.9.dist-info/DESCRIPTION.rst
google_news_crawler-0.3.9.dist-info/METADATA
google_news_crawler-0.3.9.dist-info/RECORD
google_news_crawler-0.3.9.dist-info/WHEEL
google_news_crawler-0.3.9.dist-info/entry_points.txt
google_news_crawler-0.3.9.dist-info/metadata.json
google_news_crawler-0.3.9.dist-info/top_level.txt
