Metadata-Version: 2.0
Name: google-news-crawler
Version: 0.3.9
Summary: Google News Crawler
Home-page: https://bitbucket.org/ilps/google_news_crawler
Author: Isaac Sijaranamual
Author-email: isaacsijaranamual@gmail.com
License: Apache License, Version 2.0
Keywords: Google News crawling RSS Atom feed download corpus creation
Platform: UNKNOWN
Classifier: Development Status :: 4 - Beta
Classifier: Environment :: Console
Classifier: Intended Audience :: Science/Research
Classifier: License :: OSI Approved :: Apache Software License
Classifier: Operating System :: OS Independent
Classifier: Programming Language :: Python :: 2.7
Classifier: Topic :: Internet :: WWW/HTTP
Classifier: Topic :: Text Processing :: Linguistic
Classifier: Topic :: Utilities
Requires-Dist: docopt
Requires-Dist: elasticsearch
Requires-Dist: feedparser
Requires-Dist: lxml
Requires-Dist: pytz
Requires-Dist: pyyaml
Requires-Dist: requests
Requires-Dist: tldextract
